aa/__init__.py
aa/entry_points.py
aa/plug_point_config.py
aa/business_logic/authenticator.py
aa/business_logic/authorizer.py
aa/business_logic/report_generator.py
aa/business_logic/report_initiator.py
aa/business_logic/report_validator.py
aa/plugs/event_report_loaded_plug_in.py
aa/plugs/event_report_loaded_plug_point.py
aa/plugs/generated_aa_report_plug_in.py
aa/plugs/generated_aa_report_plug_point.py
aa/plugs/initiate_report_generation_plug_in.py
aa/plugs/initiate_report_generation_plug_point.py
aa/plugs/report_status_plug_in.py
aa/plugs/report_status_plug_point.py
aa/plugs/source_aa_data_plug_in.py
aa/plugs/source_aa_data_plug_point.py
monad_aa-0.0.14.dist-info/LICENSE
monad_aa-0.0.14.dist-info/METADATA
monad_aa-0.0.14.dist-info/WHEEL
monad_aa-0.0.14.dist-info/top_level.txt
monad_aa-0.0.14.dist-info/RECORD
