Metadata-Version: 2.1
Name: monad-aa
Version: 0.0.14
Summary: monad for concept aa
Author-email: Dinesh Kamath <dmkamath@gmail.com>
Project-URL: Homepage, https://github.com/dmkamath/quick_bytes
Project-URL: Bug Tracker, https://github.com/dmkamath/quick_bytes/issues
Classifier: Programming Language :: Python :: 3
Classifier: License :: OSI Approved :: MIT License
Classifier: Operating System :: OS Independent
Requires-Python: >=3.9
License-File: LICENSE
Requires-Dist: boa-fm (==0.0.11)
